<?xml version="1.0" encoding="UTF-8" standalone="no"?>
<!DOCTYPE properties SYSTEM "http://java.sun.com/dtd/properties.dtd">
<properties>
  <comment>
    Model parameter definition
    ==========================
      Model : Pump 
      Type  : NDM200
    Parameters
    ----------
      PressureSamples [Pa]
        Array of operation points for the pump
      MassFlowSamples [l/min]
        Array of corresponding mass floes to the given pressure
        samples
      GasPressureInitial [Pa] 
      	Initial pressure of the gas
      GasVolumeInitial [m3] 
      	Initial volume of the gas
      FluidVolumeInitial [m3] 
        Initial volume of the fluid
      PressureMax [Pa] 
      	Pump turn off value
      PressureMin [Pa] 
        Pump turn on value
      
  </comment>
  <entry key="PressureSamples">1000000 14000000 15500000 16000000</entry>
  <entry key="VolFlowSamples">21 20 19.8 0</entry>
  <entry key="PowerSamples">6300 6200 6100 0</entry>
  <entry key="GasPressureInitial">6000001</entry> 
  <entry key="GasVolumeInitial">0.00195</entry>
  <entry key="FluidVolumeInitial">0.0005</entry>
  <entry key="PressureMax">7000000</entry>
  <entry key="PressureMin">6000000</entry>
</properties>
